ballmatro/__init__.py
ballmatro/card.py
ballmatro/generators.py
ballmatro/hands.py
ballmatro/jokers/__init__.py
ballmatro/jokers/factory.py
ballmatro/jokers/joker.py
ballmatro/jokers/planets.py
ballmatro/jokers/playedchangers.py
ballmatro/jokers/rankboosters.py
ballmatro/jokers/suitboosters.py
ballmatro/jokers/tests/test_factory.py
ballmatro/jokers/tests/test_joker.py
ballmatro/jokers/tests/test_planets.py
ballmatro/jokers/tests/test_playedchangers.py
ballmatro/jokers/tests/test_rankboosters.py
ballmatro/jokers/tests/test_suitboosters.py
ballmatro/optimizer.py
ballmatro/score.py
ballmatro/tests/__init__.py
ballmatro/tests/card_test.py
ballmatro/tests/hands_test.py
ballmatro/tests/test_generators.py
ballmatro/tests/test_optimizer.py
ballmatro/tests/test_score.py
ballmatro-0.2.0.dist-info/LICENSE
ballmatro-0.2.0.dist-info/METADATA
ballmatro-0.2.0.dist-info/WHEEL
ballmatro-0.2.0.dist-info/RECORD
