Metadata-Version: 2.3
Name: ballmatro
Version: 0.2.0
Summary: A challenging task for LLMs in which they need to create high-scoring Ballatro-like hands
Author: Álvaro Barbero Jiménez
Requires-Python: >=3.9,<3.14
Classifier: Programming Language :: Python :: 3
Classifier: Programming Language :: Python :: 3.9
Classifier: Programming Language :: Python :: 3.10
Classifier: Programming Language :: Python :: 3.11
Classifier: Programming Language :: Python :: 3.12
Classifier: Programming Language :: Python :: 3.13
Requires-Dist: datasets (>=3.6.0,<4.0.0)
